{"level_001":{"b":"ECAKTH","c":8,"d":8,"e":["4,1,H,ACHT","0,5,H,AKTE","3,4,V,HECK","6,0,V,CHAT","1,2,H,HACK","4,0,V,HAKT","0,7,H,HECKT","1,2,V,HACKTE"]},"level_002":{"b":"EEDURSA","c":11,"d":9,"e":["0,5,H,ERDE","4,0,V,EUER","4,0,H,EURE","5,5,H,RAUS","6,0,V,REDE","4,3,H,REED","5,5,V,REUE","2,4,V,ADER","10,4,V,RAUE","7,3,V,DAUER","0,2,V,SAUER","0,2,H,SAURE","4,7,H,AUSREDE"]},"level_003":{"b":"ÖIRGGEH","c":7,"d":6,"e":["3,2,H,HÖR","5,0,V,IHR","6,3,V,IRE","0,0,V,GIER","3,2,V,HIER","2,4,H,GEHÖR","0,0,H,GEHÖRIG"]},"level_004":{"b":"AHENIMN","c":10,"d":9,"e":["6,5,H,HEIM","3,5,V,MANN","0,8,H,MEIN","1,2,V,NAHE","0,5,V,NAHM","9,3,V,NAME","0,5,H,NEHM","7,4,V,NEIN","3,7,H,NAMEN","0,3,H,MANIE","4,0,V,NAHEM","2,0,H,EINNAHM"]},"level_005":{"b":"UFAHRRU","c":9,"d":7,"e":["4,4,H,AUF","0,6,H,RUF","2,3,H,RAR","5,0,V,RAU","6,2,V,HUF","0,3,V,FAHR","4,2,V,FRAU","4,2,H,FUHR","2,3,V,RAUF","2,0,H,AUFRUHR"]},"level_006":{"b":"ECETHIB","c":11,"d":10,"e":["7,7,V,BEI","6,3,H,EHE","3,6,V,HEB","10,5,V,TEE","1,3,V,BEET","7,7,H,BETE","7,5,H,ECHT","3,6,H,HEBT","6,1,V,HIEB","3,8,H,BIETE","8,3,V,EICHE","0,4,H,TEICH","4,0,V,BEICHTE"]},"level_007":{"b":"EÖCKHLN","c":7,"d":7,"e":["3,6,H,ECK","3,4,V,ÖLE","6,2,V,LENK","3,4,H,ÖLEN","0,2,V,KELCH","0,0,HB,KÖCHE","0,2,H,KNÖCHEL"]},"level_008":{"b":"SEHILCF","c":13,"d":12,"e":["10,3,V,EIL","9,5,V,EIS","9,5,H,ELF","9,3,H,SEH","7,6,H,SEI","7,6,V,SIE","5,8,V,FELS","5,8,H,FIEL","3,10,H,HILF","3,7,V,LEIH","1,5,V,LIEF","9,0,V,LIES","0,7,H,SEIL","4,2,V,SIEH","11,0,V,ELCH","1,5,H,LIEH","2,2,H,FISCH","0,0,HB,FLIEH","6,0,V,SCHIEF","6,0,H,SCHLIEF"]},"level_009":{"b":"NNRDEÄB","c":9,"d":9,"e":["6,2,V,DER","1,7,H,DENN","4,6,H,RENN","4,4,H,DERB","2,4,V,BÄDER","7,4,V,BÄNDE","3,2,H,BÄNDER","0,0,VB,ÄNDERN","4,1,V,BÄNDERN"]},"level_010":{"b":"THOTCRS","c":12,"d":10,"e":["8,7,V,OHR","5,6,V,ORT","9,5,H,OST","4,6,H,ROT","4,4,V,TOR","9,4,V,ROH","2,1,V,CHOR","8,9,H,ROST","0,4,H,HORST","4,8,H,STROH","11,5,V,TROST","0,2,H,SCHOTT","4,0,HB,STORCH","0,2,V,SCHROTT"]},"level_011":{"b":"LEATST","c":8,"d":6,"e":["1,3,H,ALTE","4,2,H,LAST","4,2,V,LEST","1,2,V,SATT","1,5,H,TASTE","7,0,V,SATTEL","0,0,HB,LASTET"]},"level_012":{"b":"GDLEIA","c":13,"d":12,"e":["2,4,H,DIE","3,6,V,EID","0,8,V,GEL","0,10,H,LAG","2,6,H,LEG","2,3,V,ADEL","4,1,V,ALGE","5,8,V,EGAL","0,8,H,GELD","6,2,V,LADE","5,5,H,LEID","6,2,H,LIED","8,0,V,LIEG","2,8,V,LIGA","4,9,H,IGEL","7,5,V,IDEAL","8,0,H,LEDIG","12,0,V,GILDE","2,11,H,ADELIG","10,4,VB,ADLIGE"]},"level_013":{"b":"APGNAUR","c":8,"d":8,"e":["3,4,H,ARG","4,2,V,GAR","5,0,V,NUR","0,0,V,PUR","5,6,H,RAN","0,2,H,RAP","4,2,H,GRAU","0,7,HB,PAAR","7,4,V,RANG","1,2,V,AURA","5,4,V,GARN","0,0,H,PAARUNG"]},"level_014":{"b":"RÄTWABS","c":11,"d":11,"e":["5,1,V,ABT","3,3,H,ART","7,1,H,AST","7,0,V,BAR","5,2,H,BÄR","3,2,V,RAT","1,2,H,WAR","5,9,H,WAS","1,2,V,WÄR","8,3,H,ÄRA","0,6,H,RÄT","0,4,V,BART","4,7,H,RAST","6,7,V,STAB","9,0,V,STAR","2,6,V,TRAB","1,8,H,WART","4,5,V,WÄRT","0,4,H,BRÄT","10,3,V,ABWÄRTS"]},"level_015":{"b":"POSTED","c":7,"d":7,"e":["5,0,V,DOSE","2,6,HB,POET","3,2,H,POST","0,1,H,POSE","3,0,V,DEPOT","0,1,V,PODEST"]},"level_016":{"b":"RTBHÜRE","c":13,"d":13,"e":["5,3,V,EHRT","0,4,H,HERB","6,0,V,HERR","6,0,H,HÜTE","9,1,H,RÜHR","3,5,H,TÜRE","3,3,H,ÜBER","9,0,V,ERBT","12,1,V,RÜBE","3,3,V,ÜBTE","9,3,H,TRÜB","7,6,H,HÜTER","10,3,V,RÜBER","8,5,V,RÜHRT","4,8,V,BRÜHE","0,0,V,BERÜHR","2,9,H,BERÜHRT"]}}