{"level_001":{"b":"UDUNRM","c":7,"d":6,"e":["2,2,H,NUR","0,3,H,UND","4,1,V,DRUM","6,0,VB,MUND","0,2,V,RUND","2,0,V,RUNDUM"]},"level_002":{"b":"TNSGRÖU","c":7,"d":6,"e":["6,2,V,RUGT","3,0,HB,STUR","4,2,V,TRUG","1,1,V,GURT","0,2,H,GUNST","0,4,H,STÖRUNG"]},"level_003":{"b":"HTRVREE","c":8,"d":8,"e":["0,3,H,EHE","5,2,H,HER","5,0,V,REH","2,0,H,EHER","2,0,V,EHRE","6,2,V,EHRT","3,4,H,HEER","3,4,V,HERR","0,6,H,TEER","0,0,V,VEREHRT"]},"level_004":{"b":"TLTEUBE","c":11,"d":9,"e":["2,6,V,LEB","5,6,V,TUT","2,8,H,BEET","7,3,H,BETE","2,3,H,BETT","0,6,H,EULE","10,2,V,LEBT","5,6,H,TUBE","8,2,V,BEULE","3,2,V,BEUTE","5,0,V,LEUTE","0,0,H,BEUTEL","0,0,V,BLUTETE"]},"level_005":{"b":"HSPCEI","c":7,"d":7,"e":["4,2,H,EIS","3,6,H,ICH","6,2,V,SEH","3,4,V,SEI","4,0,V,SIE","2,0,V,PECH","0,2,VB,SICH","3,4,H,SIEH","1,0,H,EPISCH"]},"level_006":{"b":"NTNAEEN","c":7,"d":7,"e":["1,6,H,NENN","4,2,V,ENTEN","0,0,HB,NENNT","2,2,V,TANNE","1,3,H,NANNTE","6,0,V,ANTENNE"]},"level_007":{"b":"TEFLTA","c":7,"d":6,"e":["2,2,V,ALT","4,2,H,ELF","0,3,H,TAL","2,4,H,TAFEL","0,0,V,FALTE","5,0,V,FALTET"]},"level_008":{"b":"EURRLAS","c":9,"d":9,"e":["1,6,V,ALS","4,6,V,AUE","4,6,H,AUS","6,4,V,LAS","0,6,H,LAU","6,4,H,LES","5,0,V,RAR","5,2,H,RAU","3,0,V,REAL","1,8,H,SAUER","7,0,V,SAURE","0,0,H,SAURER","0,0,V,SURREAL"]},"level_009":{"b":"EONFFH","c":7,"d":6,"e":["2,1,V,HOF","5,0,V,OFEN","0,2,V,OHNE","2,1,H,HOFFE","2,5,HB,OFFEN","0,3,H,HOFFEN"]},"level_010":{"b":"ROTFMKO","c":8,"d":7,"e":["4,1,H,FORM","3,3,V,FORT","0,4,H,FOTO","5,0,V,MOOR","7,1,V,MOTOR","3,3,H,FORMT","1,0,V,KOMFORT"]},"level_011":{"b":"KMAORV","c":7,"d":5,"e":["4,0,V,ARM","6,2,VB,KAM","3,2,V,OMA","2,2,H,VOM","0,0,V,VOR","1,4,H,KRAM","0,0,H,VORKAM"]},"level_012":{"b":"WBAETHC","c":11,"d":9,"e":["0,3,H,ABT","5,0,V,HAT","4,7,H,HEB","4,5,H,ACHT","7,2,V,ECHT","2,2,H,HABT","6,5,V,HEBT","2,0,V,WEHT","7,3,H,CHAT","2,0,H,WACHT","0,0,V,BEWACH","4,2,V,BEWACHT"]},"level_013":{"b":"MEÄZTHG","c":8,"d":7,"e":["0,0,H,GEH","6,0,V,ZEH","0,2,H,ZÄH","2,4,H,GEHT","2,2,V,HEGT","4,2,H,MÄHT","4,0,V,GEMÄHT","0,0,V,GEZÄHMT"]},"level_014":{"b":"EKVRAFU","c":7,"d":7,"e":["0,2,H,FRAU","3,6,HB,KAUF","3,1,H,RAUF","3,1,V,RUFE","0,4,H,RAUE","5,0,V,KURVE","1,0,V,VERKAUF"]},"level_015":{"b":"GSOREB","c":8,"d":7,"e":["6,4,V,EGO","5,6,H,SOG","1,4,V,GEO","5,1,V,GROB","0,0,HB,OBER","0,6,H,ROSE","3,4,H,ROBE","3,2,V,SORGE","1,2,H,BESORG"]},"level_016":{"b":"ISSNTEEG","c":12,"d":11,"e":["9,6,H,EIN","9,9,H,ENG","9,8,V,GEN","9,4,H,NIE","5,8,V,TEE","11,1,V,ENTE","7,1,V,TEIG","7,2,H,EIGEN","9,2,V,GENIE","11,6,V,NEIGT","4,4,V,NEIGE","0,5,H,EIGNE","0,8,H,EIGNET","0,0,V,GIESSE","0,0,H,GIESST","3,10,H,GIESSEN"]}}