{"level_001":{"b":"GRNBUEW","c":9,"d":8,"e":["5,0,V,BUG","0,2,V,GEB","6,4,H,NUR","2,7,H,WEG","2,0,V,WER","8,2,V,BERG","4,4,V,BURG","0,2,H,GERN","3,5,H,RUGE","5,2,H,GRUB","6,2,V,RUNE","2,0,H,WERBUNG"]},"level_002":{"b":"NEIDWE","c":11,"d":11,"e":["7,6,V,DEN","8,4,H,DIE","5,8,V,EID","5,8,H,EIN","3,8,V,NIE","1,8,H,WEN","2,6,V,WIE","7,6,H,DEIN","8,3,V,IDEE","2,10,H,NEID","10,3,V,WEIN","2,6,H,WIND","4,3,V,DIENE","0,2,VB,IDEEN","2,4,H,WEIDE","6,0,V,WENDE","5,1,H,WEIDEN"]},"level_003":{"b":"DBNRMAA","c":8,"d":7,"e":["1,4,V,ARM","5,4,V,BAD","5,4,H,BAR","3,6,H,RAD","2,2,V,RAN","0,4,H,BAND","7,2,V,DARAN","0,0,HB,DRAMA","1,2,H,ARMBAND"]},"level_004":{"b":"EZEITRT","c":14,"d":12,"e":["0,5,H,EIER","0,4,V,REIZ","2,3,H,RITT","3,2,V,TIER","0,7,H,ZEIT","3,10,H,RIET","3,7,V,TEER","5,8,V,ZIER","7,4,V,REITE","7,2,HB,RETTE","5,5,H,TEERT","9,5,V,TRETE","9,6,H,REIZT","5,8,H,ZIERT","5,0,V,REITET","11,5,V,ZITTERE"]},"level_005":{"b":"IMKCSHO","c":8,"d":7,"e":["0,3,H,ICH","5,3,H,IHM","5,1,V,SKI","2,0,V,KOCH","7,3,V,MICH","4,6,H,SICH","0,2,V,MISCH","1,1,H,KOMISCH"]},"level_006":{"b":"NGAESS","c":8,"d":8,"e":["4,5,H,GANS","0,1,VB,GASE","2,3,H,NASE","2,3,V,NASS","4,3,V,SAGE","4,0,H,SANG","5,0,V,ASSE","0,6,H,GASSE","7,2,V,GASSEN"]},"level_007":{"b":"NUIIGNE","c":7,"d":7,"e":["4,2,V,NEU","0,1,H,NUN","2,1,V,NEIN","2,4,H,NEUN","2,2,H,EINIG","2,6,HB,INNIG","0,0,V,UNEINIG"]},"level_008":{"b":"THGUSEC","c":13,"d":12,"e":["0,10,H,EUCH","3,8,V,GEHT","3,8,H,GUTE","6,7,V,HEUT","2,3,V,SEHT","1,6,H,STEH","9,7,V,SUCH","6,10,H,TUCH","10,4,V,HEGT","9,7,H,STEG","8,4,H,SCHEU","5,1,H,SUCHT","8,1,V,HEGST","6,0,V,HUSTE","1,6,V,SCHEUT","0,3,H,GESUCHT"]},"level_009":{"b":"LELTFÜR","c":7,"d":7,"e":["4,4,H,ELF","6,4,V,FÜR","2,0,V,FELL","0,3,V,FÜLL","0,3,H,FÜLLT","4,0,V,LÜFTE","0,0,H,ERFÜLLT"]},"level_010":{"b":"ITEGRA","c":11,"d":10,"e":["4,6,V,GART","9,5,V,GIER","2,6,V,RATE","1,9,H,REGT","7,5,H,TAGE","1,6,H,TRAG","0,4,H,ARIE","1,3,V,GRAT","4,8,H,RAGE","3,1,V,GARE","2,2,H,RAGT","5,0,V,ARTIG","7,5,V,TIGER","5,0,H,AGIERT"]},"level_011":{"b":"AURFUF","c":6,"d":5,"e":["0,2,V,AUF","2,0,V,RUF","3,2,V,RAU","0,4,H,FRAU","2,0,H,RAUF","0,2,H,AUFRUF"]},"level_012":{"b":"NAGKEAL","c":14,"d":13,"e":["5,8,H,ALGE","8,8,V,EGAL","8,11,H,LAGE","10,8,V,LANG","2,10,H,NAGE","12,5,V,ELAN","10,6,H,GALA","10,8,H,LENK","8,3,H,AALE","4,0,V,ANGEL","2,2,H,ANGLE","8,2,V,KANAL","2,0,V,KLAGE","10,2,V,KLANG","4,4,H,LAKEN","5,7,V,NAGEL","0,0,V,ALGEN","3,7,V,ANLAGE","0,6,VB,KLAGEN","0,0,H,ANKLAGE"]},"level_013":{"b":"CLISEUS","c":7,"d":7,"e":["0,4,V,EIL","0,4,H,EIS","0,2,H,ISS","2,0,V,LES","1,2,V,SEI","2,4,V,SIE","0,6,H,LIES","5,2,VB,SEIL","0,0,H,CELSIUS"]},"level_014":{"b":"HUREERB","c":12,"d":12,"e":["3,6,V,EHE","2,4,V,HEB","3,2,V,HER","3,2,H,HEU","6,11,H,REH","8,9,V,RUH","1,4,H,UHR","6,8,V,EHER","4,0,HB,EHRE","0,6,H,ERBE","9,6,V,EUER","3,8,H,EURE","8,6,H,HEER","8,3,H,HERB","6,9,H,HERR","10,3,V,REBE","9,0,V,REUE","5,2,V,URHEBER"]},"level_015":{"b":"UGEAZS","c":8,"d":8,"e":["4,4,V,AUE","5,0,V,GAS","5,2,H,SAG","3,0,H,ZUG","6,2,V,AUGE","0,2,H,ZEUG","3,4,H,SAUG","3,0,V,ZUGES","0,2,V,ZUSAGE"]},"level_016":{"b":"SONRET","c":13,"d":13,"e":["8,6,V,NOT","6,8,V,ORT","6,8,H,OST","10,4,V,ROT","2,12,H,TON","4,9,H,TOR","9,4,H,ERST","2,9,V,NEST","12,1,V,REST","9,2,H,ROSE","7,0,H,ROST","6,6,H,ERNST","7,0,V,ROSEN","9,0,V,SORTE","4,8,V,STERN","3,4,H,TOSEN","4,1,V,TENOR","1,2,V,OSTERN","0,2,H,SORTEN"]}}