{"level_001":{"b":"EPCERO","c":10,"d":8,"e":["6,4,H,CREE","8,1,V,PERE","1,1,H,PORC","2,1,V,OREE","4,2,H,OPERE","0,4,H,CREPE","6,1,V,PERCE","0,3,V,ECOPE","4,0,V,ECOPER"]},"level_002":{"b":"GEIENT","c":8,"d":8,"e":["4,2,H,GENE","0,3,H,TIEN","2,0,V,GITE","0,3,V,TIGE","7,1,V,GENT","5,0,V,NIET","0,5,H,GENIE","3,3,V,NEIGE","2,0,H,GEINT","2,7,H,TEIGNE"]},"level_003":{"b":"RUAARCE","c":10,"d":8,"e":["1,3,V,AURA","3,0,V,CRUE","6,4,V,CURE","0,3,H,RARE","4,4,H,RECU","2,1,H,CREA","5,1,V,ACRE","4,4,V,RUER","0,6,H,CARRE","5,2,H,CURER","9,0,V,CARREAU"]},"level_004":{"b":"TILEMI","c":10,"d":10,"e":["4,0,V,ILE","4,1,H,LIE","8,2,V,LIT","3,4,V,MEL","6,0,V,MET","1,2,V,MIT","6,2,H,TEL","6,4,V,MIE","5,6,V,MIEL","1,2,H,MILE","0,4,H,ITEM","3,6,H,LIME","5,4,H,IMITE","0,8,H,LIMITE"]},"level_005":{"b":"TULRAAD","c":9,"d":7,"e":["3,1,V,AURA","8,3,V,LARD","0,4,H,TARA","5,6,H,TARD","6,1,V,ARDU","5,4,H,DURA","1,0,V,ULTRA","1,2,H,TAULARD"]},"level_006":{"b":"ITTNOR","c":9,"d":8,"e":["4,6,H,NOIR","6,3,V,ROTI","0,2,H,TOIT","5,0,V,TORT","0,2,V,TRIO","5,3,H,TROT","4,4,V,TINT","0,4,H,IRONT","2,0,V,TRITON"]},"level_007":{"b":"RETTDA","c":11,"d":8,"e":["7,5,H,ETAT","10,3,V,RATE","6,0,H,TARD","9,0,V,DATE","3,4,H,RADE","8,3,V,TATE","6,0,V,TARTE","4,3,V,DATER","6,3,H,TATER","0,7,H,TETARD"]},"level_008":{"b":"URHITE","c":8,"d":8,"e":["4,3,H,HIER","0,2,H,HUIT","2,0,H,TIRE","5,0,V,ETUI","4,3,V,HUER","4,6,H,RITE","2,0,V,TRIE","7,2,V,TRUIE","0,2,V,HUITRE"]},"level_009":{"b":"LIIORS","c":9,"d":7,"e":["3,2,V,IRIS","5,3,H,LOIS","0,2,H,LORI","0,2,V,LORS","8,0,V,ROIS","3,5,H,SOIR","6,0,V,SILO","5,3,V,LOIR","3,0,H,LOISIR"]},"level_010":{"b":"TIEFHEC","c":10,"d":8,"e":["2,5,V,CET","2,5,H,CHI","4,6,H,ETE","2,1,V,FEE","0,7,H,FIT","6,4,V,THE","4,4,V,FIE","0,2,H,CHEF","7,1,V,CITE","4,4,H,FETE","5,1,H,FICHE","0,2,V,CHETIF","9,0,V,FETICHE"]},"level_011":{"b":"NROSSE","c":12,"d":9,"e":["0,4,V,NES","0,4,H,NOS","1,2,H,OSE","2,2,V,SES","5,6,V,SON","3,0,V,NOE","3,8,H,SENS","5,0,V,SERS","3,5,V,SORS","3,1,H,OSER","8,3,V,ROSE","8,4,H,ORNE","4,3,H,ESSOR","11,0,V,ROSSE","0,6,H,SERONS"]},"level_012":{"b":"ESASLR","c":8,"d":8,"e":["4,6,H,RASE","3,0,H,SALE","4,4,V,SERA","3,0,V,SERS","0,1,H,RALE","4,4,H,SELS","0,3,H,ARES","0,1,V,REAL","5,0,V,LASSE","7,2,V,LASSER"]},"level_013":{"b":"ICVRAA","c":9,"d":9,"e":["6,1,V,AIR","4,1,V,ARC","4,3,H,CAR","2,0,V,CRI","6,2,H,IRA","6,5,H,VIA","0,2,H,RAI","2,1,H,RIA","8,2,V,ARIA","0,2,V,RAVI","6,5,V,VRAI","0,4,H,VRAC","3,4,V,CRIA","2,7,H,CAVIAR"]},"level_014":{"b":"VROOUSN","c":10,"d":10,"e":["6,1,V,NOS","4,2,V,NUS","2,2,H,SON","2,2,V,SOU","5,6,V,SUR","4,3,H,UNS","3,6,V,VOS","3,6,H,VUS","6,1,H,NOUS","1,4,H,OURS","0,8,H,VOUS","1,4,V,OURSON","8,0,V,OUVRONS"]},"level_015":{"b":"ENSEPT","c":11,"d":8,"e":["3,5,H,ETES","7,4,H,SENT","3,4,V,SEPT","0,4,H,NEES","7,1,V,NETS","2,1,V,PESE","5,1,H,PENSE","5,1,V,PENTE","1,2,H,PESTE","9,0,V,PESENT"]},"level_016":{"b":"EACFFTE","c":11,"d":8,"e":["7,1,H,ACTE","0,4,H,CAFE","7,0,V,FACE","10,0,V,FETE","1,6,H,EFFET","3,3,H,TAFFE","3,0,V,CAFTE","1,1,V,EFFACE","5,1,V,AFFECTE"]},"level_017":{"b":"NAPLRAT","c":12,"d":10,"e":["10,3,V,ART","7,0,V,LPT","9,3,H,PAN","7,1,H,PAR","8,5,H,PAT","9,1,V,RAP","5,2,H,RAT","5,0,V,PART","8,5,V,PLAN","2,3,H,PLAT","5,7,H,TARA","5,5,V,NATAL","2,3,V,PARLA","0,5,V,PLANT","0,5,H,PARLANT"]},"level_018":{"b":"AARNDEV","c":12,"d":9,"e":["6,0,V,REND","3,3,H,VEND","0,2,H,NADA","3,1,H,RADE","3,1,V,RAVE","4,7,H,DEVRA","5,3,V,NAVRE","7,4,V,AVARE","7,4,H,AVERA","0,0,V,VENDRA","11,1,V,VERANDA"]},"level_019":{"b":"ARTSOG","c":11,"d":9,"e":["4,1,H,ARTS","9,1,V,GARS","6,4,H,GRAS","6,4,V,GROS","3,7,H,RATS","3,5,V,SORT","7,1,V,STAR","7,2,H,TSAR","0,5,H,TAGS","0,1,V,ARGOT","4,0,V,RAGOT","0,3,H,GRATOS"]},"level_020":{"b":"LISGEL","c":7,"d":7,"e":["0,0,V,GEL","4,2,H,ILE","4,2,V,ILS","2,0,V,LES","6,4,V,LIE","0,2,H,LIS","5,0,V,SEL","4,4,H,SIL","2,6,H,SIGLE","0,0,H,GILLES"]},"level_021":{"b":"TDNANFO","c":10,"d":10,"e":["0,7,V,DAN","6,4,V,DON","6,4,H,DOT","4,6,V,FAN","7,2,H,NON","8,2,V,ONT","7,0,V,TON","5,0,H,FAT","0,4,H,DONT","5,0,V,FOND","4,6,H,FONT","2,2,H,FAON","0,1,V,TOND","0,7,H,DONNA","2,2,V,FONDANT"]},"level_022":{"b":"EEDCAR","c":10,"d":10,"e":["4,9,H,CEDE","6,3,V,CREE","6,3,H,CADE","7,0,V,CREA","7,6,V,RADE","5,6,V,ACRE","5,6,H,AERE","4,1,H,CADRE","4,1,V,CEDER","0,2,H,CEDRE","0,2,V,CEDERA"]},"level_023":{"b":"EIDLMME","c":10,"d":9,"e":["6,1,H,DEMI","6,6,H,IDEE","8,3,V,LIEE","6,3,H,MELE","3,7,H,MEME","6,5,V,MIEL","9,0,V,MILE","6,0,V,IDEM","4,4,V,LIME","1,1,V,MIME","1,4,H,EMILE","0,2,H,DILEMME"]},"level_024":{"b":"CEVIER","c":9,"d":9,"e":["1,5,H,CREE","1,5,V,CRIE","4,5,V,ERIC","7,3,V,IVRE","5,4,H,REVE","4,6,H,RIVE","2,3,H,VIRE","0,0,H,CIRE","0,0,V,CREVE","5,0,V,EVIER","3,0,V,ECRIVE"]},"level_025":{"b":"HCEZRAC","c":11,"d":11,"e":["0,6,H,CHAR","4,1,H,CHER","4,1,V,CHEZ","7,0,V,CRAC","2,3,V,CREA","7,2,H,ACRE","9,1,V,ARCHE","0,3,H,CACHE","5,5,H,CACHER","5,5,V,CACHEZ","5,7,H,CRACHE","0,3,V,CRACHEZ"]},"level_026":{"b":"NVHAIE","c":10,"d":8,"e":["5,6,H,HEIN","8,3,V,VAIN","1,2,V,HAIE","0,4,H,AINE","3,1,V,VINE","7,0,V,ENVI","1,2,H,HAINE","5,3,H,NAIVE","5,2,V,ENVAHI"]},"level_027":{"b":"EUEDLEG","c":10,"d":9,"e":["5,2,V,DUE","3,3,H,ELU","5,4,H,EUE","3,2,V,GEL","2,6,V,LUE","7,3,H,GLU","4,6,V,GUE","0,4,H,DUEL","1,3,V,LUGE","9,0,V,LEGUE","7,1,V,DEGEL","0,6,H,DELUGE","1,8,H,DELEGUE"]},"level_028":{"b":"REVSEA","c":12,"d":9,"e":["9,1,V,ARE","11,1,V,ERE","10,3,V,RAS","8,5,H,VAS","8,5,V,VER","5,6,H,REVE","6,5,V,SERA","8,1,H,VASE","3,5,V,RAVE","4,2,V,SEVE","1,5,H,AERE","7,3,H,AVERE","0,3,H,SERVE","2,8,H,VERSA","2,0,V,AVERSE"]},"level_029":{"b":"NSEMCEE","c":10,"d":8,"e":["3,1,V,MECS","0,2,H,MENE","0,2,V,MENS","7,4,V,NEES","6,6,H,SEME","6,2,H,NEMS","6,0,V,CENSE","9,2,V,SCENE","4,0,H,MECENE","3,4,H,SEMENCE"]},"level_030":{"b":"AAISPL","c":12,"d":9,"e":["3,4,V,AIL","4,8,H,AIS","2,6,H,ILS","6,6,V,LAS","6,6,H,LIS","8,4,V,PAS","8,4,H,PIS","4,6,V,SPA","9,2,V,PLI","2,1,H,SIL","8,0,V,LIA","7,2,H,LAPS","2,1,V,SALI","0,4,H,ALIAS","4,0,V,PLAIS","6,0,H,PALAIS"]},"level_031":{"b":"BZISER","c":13,"d":10,"e":["5,4,H,RIS","5,4,V,RIZ","10,0,V,RIE","7,2,V,BIS","2,6,H,IREZ","3,6,V,RIEZ","0,8,H,SIRE","7,2,H,BISE","9,0,H,BRIS","9,4,H,BRIE","0,5,V,BRISE","12,0,V,SBIRE","9,4,V,BRISEZ"]}}