{"level_001":{"b":"IDTUAM","c":9,"d":8,"e":["6,4,H,AIT","2,6,H,AMI","3,2,V,DIT","4,5,H,MAI","4,5,V,MIT","0,5,H,DAM","2,5,V,MAT","8,2,V,DUT","6,3,V,DAIM","0,3,H,AUDIT","0,0,HB,ADMIT","0,2,V,MAUDIT"]},"level_002":{"b":"BDEILA","c":10,"d":9,"e":["5,5,V,AIDE","2,8,H,BAIE","6,2,H,BAIL","3,5,V,DELA","8,0,V,LAID","6,2,V,BALI","0,6,H,BILE","5,5,H,AILE","1,2,V,DELAI","0,2,H,IDEAL","4,0,V,DELIA","4,0,H,DIABLE"]},"level_003":{"b":"EEIBST","c":8,"d":7,"e":["5,3,H,EST","5,2,V,SET","3,2,H,TES","1,0,H,BIS","0,3,H,BETE","3,0,V,SITE","1,0,V,BISE","0,3,V,BITS","7,1,V,BETISE"]},"level_004":{"b":"ERLRAMA","c":15,"d":12,"e":["5,10,H,AME","0,5,V,MAL","3,8,H,MEL","7,9,V,MER","5,8,V,LEA","3,7,V,AMER","10,6,V,ARME","7,9,H,MALE","10,7,H,RARE","0,7,H,LAMA","13,4,V,RALE","11,5,H,REAL","9,2,H,LARME","11,1,V,ARMER","9,0,V,RALER","5,4,H,RAMER","5,2,V,MARRE","1,2,H,ALARME","3,0,V,AMARRE","3,0,H,ALARMER"]},"level_005":{"b":"OSNCAN","c":7,"d":6,"e":["6,2,V,ANS","0,5,HB,CAS","0,3,H,NON","4,4,H,NOS","2,0,H,SAC","0,1,V,SON","0,1,H,SOC","2,0,V,SCAN","4,0,V,CANONS"]},"level_006":{"b":"HSFOCIN","c":10,"d":8,"e":["2,2,V,COIN","1,0,HB,FINS","6,1,V,FOIN","6,1,H,FOIS","5,4,H,INFO","0,4,H,SOIF","0,4,V,SOIN","5,4,V,IONS","2,2,H,CHINO","8,0,V,FICHONS"]},"level_007":{"b":"ULEQUD","c":6,"d":7,"e":["2,3,V,ELU","0,3,H,QUE","2,4,H,LUE","4,2,V,DUEL","2,0,HB,QUEL","0,1,V,DUQUEL"]},"level_008":{"b":"URULTCE","c":12,"d":11,"e":["9,7,H,CET","7,8,V,TEL","6,6,V,CRU","7,9,H,EUT","5,4,H,RUE","6,6,H,CRUE","5,2,V,CURE","7,3,V,LEUR","3,2,H,RECU","3,1,V,TRUC","0,3,H,RELU","4,8,H,CRUT","0,2,V,CRUEL","5,0,HB,CULTE","0,6,H,LUEUR","4,6,V,RECUL","9,5,V,RECUT","11,4,V,CULTURE"]},"level_009":{"b":"ZTNSEE","c":8,"d":7,"e":["6,4,V,ETE","4,4,V,NEE","5,2,V,NET","3,0,V,NEZ","3,2,H,ZEN","1,0,H,SENT","3,6,H,TENEZ","0,2,VB,ZESTE","2,4,H,SENTEZ"]},"level_010":{"b":"SVIEAG","c":11,"d":11,"e":["8,4,H,AGE","7,6,H,AGI","7,6,V,AIE","3,10,H,AIS","9,4,V,GAI","5,8,V,VAS","3,8,V,VIA","5,8,H,VIE","1,6,H,VIS","7,1,H,AVIS","10,1,V,SAGE","3,3,V,VAIS","1,6,V,VASE","8,1,V,VISA","4,0,V,AISE","1,3,H,GAVE","0,9,H,GEAI","1,0,H,VISAGE"]},"level_011":{"b":"VEEENR","c":6,"d":6,"e":["3,4,H,ERE","0,5,H,VER","5,1,V,REVE","3,0,V,VERNE","0,2,H,ENERVE","1,0,V,VENERE"]},"level_012":{"b":"TUUSBOA","c":13,"d":12,"e":["0,8,V,BAS","0,5,H,BAT","2,3,V,BUT","2,9,H,OUT","0,10,H,SOU","3,0,H,TAS","2,3,H,BAU","0,8,H,BOA","5,0,V,SUT","5,2,H,TUS","2,8,V,AOUT","1,5,V,AUTO","9,3,H,BOUT","7,2,V,SAUT","7,5,H,TOUS","3,0,V,TUBA","4,5,V,SABOT","9,1,V,TABOU","8,7,H,OBTUS","12,1,V,AUTOBUS"]},"level_013":{"b":"CIDCEL","c":8,"d":6,"e":["3,0,V,ILE","3,1,H,LIE","0,0,V,CIL","0,0,H,CECI","7,0,VB,CIEL","2,2,V,CLIC","0,2,H,LICE","5,0,V,DECLIC"]},"level_014":{"b":"EATPRN","c":11,"d":10,"e":["7,7,V,ANE","6,4,V,ARE","8,4,H,ART","4,6,V,PAN","8,3,V,PAT","6,5,H,RAT","4,6,H,PRE","2,4,V,PART","0,2,V,PATE","0,2,H,PRET","0,4,H,TAPE","7,7,H,APTE","10,4,V,TAPER","3,0,V,ANTRE","0,7,H,ENTRA","2,0,H,PARENT"]},"level_015":{"b":"LCICAUM","c":7,"d":7,"e":["4,4,V,AIL","3,0,V,LAC","2,2,V,LUI","4,6,H,LIA","0,0,H,MAIL","1,4,H,LIMA","0,0,V,MICA","0,2,H,CALCIUM"]},"level_016":{"b":"ESTUQUR","c":9,"d":8,"e":["2,4,V,RUES","0,7,H,RUSE","3,3,H,SURE","0,4,V,SUER","6,1,V,SUEUR","0,5,H,USURE","4,0,V,SUTURE","8,0,VB,TRUQUE","0,1,H,TURQUES"]}}