{"level_001":{"b":"NRREIA","c":9,"d":9,"e":["0,3,H,AIRE","5,3,H,NIER","3,0,V,RARE","5,0,V,REIN","1,2,V,RIEN","7,0,V,RIRE","2,1,H,RAIE","4,5,V,RIRA","1,5,H,NIERA","4,7,H,RAINE","8,3,V,RAINER"]},"level_002":{"b":"NNSREAO","c":12,"d":10,"e":["4,1,V,RASE","8,1,H,SERA","1,4,V,ANES","0,6,H,NEON","8,0,V,OSER","1,4,H,ANSE","11,1,V,ARES","3,9,H,ROSE","6,5,V,SONNE","9,4,V,OSERA","4,3,H,SONAR","3,4,V,SONNER","5,6,H,SONNERA"]},"level_003":{"b":"XEEHUUR","c":7,"d":5,"e":["3,0,V,EUE","6,0,V,EUX","1,2,V,HUE","4,2,V,RUE","1,2,H,HUER","2,0,H,HEURE","0,4,H,HEUREUX"]},"level_004":{"b":"ARBOELE","c":13,"d":13,"e":["2,2,V,ARE","1,4,V,BAL","4,1,H,BAR","1,4,H,BEL","0,6,H,BLE","0,6,V,BOL","0,8,H,LEA","4,1,V,BOA","1,2,H,LABO","2,11,H,REEL","4,8,V,ROBE","4,8,H,ROLE","10,6,V,LOBE","7,6,H,ORAL","9,9,V,RALE","7,6,V,OREE","9,9,H,REAL","6,0,V,ERABLE","6,12,H,BOREALE","2,6,V,ELABORE"]},"level_005":{"b":"SCQUIA","c":8,"d":7,"e":["6,4,V,AIS","5,4,H,CAS","0,4,V,QUI","5,2,V,SAC","5,6,H,USA","0,4,H,QUAI","0,0,HB,CUIS","2,2,V,QUASI","0,2,H,ACQUIS"]},"level_006":{"b":"AANLEI","c":13,"d":10,"e":["5,2,V,AIL","0,7,H,ANE","4,7,V,ILE","2,5,V,LIE","4,8,H,LIN","1,7,V,NIA","8,7,H,NIE","3,3,V,LIA","1,5,H,ELAN","6,5,V,LIEN","1,9,H,AILE","5,6,H,AINE","2,3,H,ALAIN","8,3,V,ALIEN","10,3,V,LAINE","8,4,H,LIANE","12,0,V,ALINEA"]},"level_007":{"b":"SBISEA","c":10,"d":9,"e":["0,4,H,AIE","1,2,H,BAS","0,6,H,SAS","2,6,V,SES","1,2,V,BAI","5,6,V,BIS","3,0,H,BAIE","3,0,V,BASE","2,8,H,SAIS","0,4,V,AISE","5,6,H,BISE","8,2,V,BASSE","6,0,V,ESSAI","4,4,H,BAISSE"]},"level_008":{"b":"PDEIOEL","c":13,"d":11,"e":["7,2,V,LOI","7,3,H,OIE","9,4,H,EPI","4,2,V,PIE","11,2,V,PLI","2,4,H,ODE","9,1,V,IDEE","0,6,H,PIED","4,2,H,POIL","2,3,V,POLE","0,6,V,POLI","0,9,H,IODE","3,6,V,DOLE","3,8,H,LIDO","5,10,H,PELE","8,7,V,PILE","6,6,V,IDOLE","3,0,HB,POELE","6,7,H,DEPLOIE"]},"level_009":{"b":"TCODNI","c":8,"d":7,"e":["2,0,V,COIN","5,1,VB,DOIT","7,3,V,DONC","3,3,V,DONT","0,0,H,DICO","0,3,H,TOND","3,6,H,TONIC","0,0,V,DICTON"]},"level_010":{"b":"OSTEPP","c":11,"d":11,"e":["1,6,V,EST","3,9,H,OSE","3,8,V,POP","7,8,V,POT","0,6,H,SET","5,8,V,TES","5,8,H,TOP","2,4,H,OTE","4,1,V,POSE","2,3,V,POST","4,1,H,POTE","7,0,V,SEPT","4,3,H,SPOT","0,8,H,STOP","6,3,V,OPTE","9,5,V,POSTE","0,0,VB,PESTO","5,5,H,STOPPE"]},"level_011":{"b":"LLEFUIL","c":9,"d":8,"e":["0,4,H,FILE","7,2,V,LIEU","5,4,H,FUEL","5,4,V,FULL","1,2,V,FUIE","2,7,H,FIEL","3,0,V,FILLE","1,2,H,FILLEUL"]},"level_012":{"b":"PETTERN","c":12,"d":11,"e":["5,1,V,PERE","3,1,V,PRET","7,3,H,TETE","9,1,V,ENTRE","1,4,H,NETTE","0,6,H,PERTE","1,2,V,TENTE","2,6,V,RENTE","1,2,H,TERNE","7,0,V,TENTER","4,8,HB,TRENTE","5,1,H,PRETENT"]},"level_013":{"b":"VYZOGAE","c":10,"d":8,"e":["6,0,V,AGE","4,5,V,GAZ","4,7,H,ZOE","2,4,V,EGO","9,2,V,AVEZ","6,5,H,AYEZ","1,6,H,YOGA","0,4,H,OYEZ","6,4,V,GAVE","3,0,V,VOYEZ","1,2,H,VOYAGE","3,0,H,VOYAGEZ"]},"level_014":{"b":"EZVENRE","c":11,"d":10,"e":["0,3,H,ERE","4,6,H,NEE","2,4,H,NEZ","6,5,V,VER","4,4,V,ZEN","6,7,H,REVE","2,2,V,VENEZ","8,5,V,REVEZ","6,5,H,VERNE","7,0,V,ENERVE","5,1,H,VENERE","10,0,V,REVENEZ","0,1,V,ENERVEZ"]},"level_015":{"b":"TERAUA","c":6,"d":6,"e":["1,2,V,AURA","3,0,V,RATE","1,0,H,TARA","5,2,V,ETAU","1,2,H,AUTRE","0,5,H,RATEAU"]},"level_016":{"b":"TQROUE","c":11,"d":9,"e":["8,1,V,OTER","5,7,H,ROUE","7,1,H,TOUR","7,4,H,TROU","5,5,V,EURO","1,5,H,ROUTE","7,4,V,TOQUE","3,2,V,ORQUE","0,3,H,OUTRE","10,1,V,ROQUE","1,0,V,TOQUER","1,0,H,TROQUE"]}}