{"level_001":{"b":"IMENEZ","c":9,"d":8,"e":["3,1,V,NEE","6,5,H,NEZ","4,4,H,MIE","0,5,H,NIE","2,6,H,ZEN","0,3,H,MENE","6,2,V,MIEN","4,4,V,MINE","2,3,V,NIEZ","0,3,V,MENEZ","8,0,V,MENIEZ"]},"level_002":{"b":"IRNISO","c":9,"d":8,"e":["0,2,H,IRIS","7,3,V,NOIR","0,0,V,ROIS","1,5,H,SOIN","4,6,H,SOIR","4,3,V,IONS","4,3,H,IRONS","2,0,HB,RIONS","2,2,V,IRIONS"]},"level_003":{"b":"VLIEDI","c":7,"d":6,"e":["0,0,V,VIE","4,2,H,VIL","6,2,V,LIVE","2,2,VB,VIDE","0,0,H,VIEIL","4,0,V,LIVIDE"]},"level_004":{"b":"SRDONE","c":13,"d":11,"e":["5,0,V,DONS","0,2,H,DORE","2,5,V,DORS","1,6,H,DOSE","2,0,H,NORD","6,7,V,REND","6,7,H,ROND","3,0,V,OSER","9,5,V,RODE","3,3,H,ROSE","4,3,V,ORNE","8,5,H,DRONE","2,8,H,SONDE","0,0,V,ENDORS","11,3,V,SONDER"]},"level_005":{"b":"RNNAOOD","c":7,"d":7,"e":["4,0,V,DAN","2,2,V,DON","0,4,H,NON","2,0,H,RAD","0,1,V,DONNA","2,6,HB,RADON","0,2,H,ORDONNA"]},"level_006":{"b":"SONATSB","c":11,"d":11,"e":["8,10,H,ANS","6,6,V,BAS","6,6,H,BON","6,4,H,NOS","4,2,V,SAS","8,4,V,SON","10,8,V,TAS","4,2,H,SOT","8,8,V,BOA","1,4,H,BOSS","3,4,V,SANS","1,6,H,SONT","0,9,H,SNOB","6,0,V,BATON","6,8,H,SABOT","1,4,V,BOSSANT"]},"level_007":{"b":"MAWLLEX","c":9,"d":8,"e":["1,2,H,AME","3,0,V,AXE","6,2,H,MAL","2,2,V,MEL","7,0,V,LEA","4,4,H,ALLE","0,4,VB,MALE","4,4,V,AXEL","6,2,V,MALLE","2,0,H,MAXWELL"]},"level_008":{"b":"STMGEEN","c":13,"d":10,"e":["2,3,V,EST","3,2,H,MES","0,5,H,MET","1,3,H,NES","0,7,H,NET","2,9,H,SET","2,7,V,TES","4,4,H,GENE","7,1,HB,GENS","0,5,V,MENS","9,3,V,MENT","4,6,V,EMET","7,3,V,SEME","12,0,V,GENT","3,0,V,NEMS","5,0,V,GESTE","7,3,H,SEMENT","3,6,H,SEGMENT"]},"level_009":{"b":"MDOLRI","c":9,"d":8,"e":["1,2,H,LOI","3,0,V,MOI","6,2,H,ROI","5,4,V,LORD","0,7,HB,LORI","3,0,H,MORD","2,2,V,ORDI","5,4,H,LIDO","0,5,H,LOIR","6,0,V,DORMI","8,1,V,MILORD"]},"level_010":{"b":"BRUXOE","c":12,"d":9,"e":["5,8,H,EUX","7,6,H,OEU","3,7,H,BRU","9,4,H,BUE","5,6,V,RUE","9,4,V,BOUE","6,0,VB,ROBE","11,1,V,ROUE","7,5,V,ROUX","0,5,H,EURO","3,5,V,ORBE","0,2,V,BOXE","0,2,H,BOXER","2,0,V,BOXEUR"]},"level_011":{"b":"NNAEOYB","c":9,"d":9,"e":["6,4,V,ANE","3,3,H,BAN","6,5,H,NOE","2,6,V,YEN","5,0,V,NEON","0,8,H,BONNE","8,1,V,ABOYE","4,3,V,ABONNE","0,6,H,BAYONNE"]},"level_012":{"b":"NLIATCA","c":13,"d":12,"e":["0,7,H,AIL","4,7,H,LAC","4,7,V,LIN","5,0,V,LIT","5,5,V,NIA","2,7,V,LIA","2,5,H,CLIN","2,2,H,LAIT","7,0,V,TAIN","5,0,H,LITA","9,2,V,TIAN","7,3,H,NAIT","0,9,H,ALAIN","11,4,V,CALIN","3,1,V,CANAL","8,7,H,LATIN","0,6,V,NATAL","7,5,H,LANCA","8,7,V,LIANT","2,11,H,LANCAIT"]},"level_013":{"b":"HABTIEZ","c":9,"d":8,"e":["2,4,V,BAIE","2,4,H,BATI","3,1,V,BETA","5,1,H,HATE","8,0,V,BEAT","0,2,H,HAIE","0,6,H,TAIE","0,2,V,HABIT","5,1,V,HABITEZ"]},"level_014":{"b":"ETEHSCN","c":11,"d":10,"e":["6,5,H,CENT","1,6,H,ETES","4,6,V,SENT","8,5,V,NEES","2,4,V,NETS","4,9,H,THES","0,4,H,CENSE","6,5,V,CHENE","1,0,V,SCENE","0,2,H,SECHE","4,0,V,THESE","4,3,H,SECHENT"]},"level_015":{"b":"LANROM","c":8,"d":8,"e":["3,0,V,MON","3,2,H,NOM","4,2,V,ORAL","1,3,V,MORAL","7,0,VB,ROMAN","0,4,H,NORMAL"]},"level_016":{"b":"EPEOTRH","c":13,"d":12,"e":["7,8,V,ETRE","9,8,V,HOTE","4,8,H,PERE","11,6,V,PORT","5,5,V,POTE","6,10,H,PRET","8,6,H,TROP","6,3,H,TOPE","9,9,H,OPTE","9,0,V,OREE","6,1,H,OPERE","8,3,V,PERTE","6,0,V,POETE","4,0,V,ETHER","0,4,H,OPTER","0,2,H,TROPHEE"]}}