{"level_001":{"a":19696,"b":"TAYTR","c":7,"d":5,"e":["0,2,H,ART","4,0,H,RAT","2,4,H,RAY","2,2,V,TAR","4,3,H,TRY","0,1,V,TART","6,0,V,TRAY","4,0,V,RATTY"]},"level_002":{"a":19711,"b":"NGTIA","c":8,"d":6,"e":["3,4,H,ANT","1,2,V,NAG","3,3,V,TAG","7,0,V,TAN","5,0,H,GIT","4,2,H,GAIN","0,0,HB,TANG","0,3,H,GAIT","5,0,V,GIANT"]},"level_003":{"a":25746,"b":"SAIMG","c":7,"d":5,"e":["6,2,V,AIM","0,0,HB,GAS","0,2,V,SIM","2,2,V,SAG","0,4,H,MAGS","2,2,H,SIGMA"]},"level_004":{"a":25751,"b":"NAILS","c":7,"d":6,"e":["3,3,V,NIL","0,5,H,NAIL","0,1,H,SAIL","5,1,V,LAIN","2,3,H,SNAIL","0,1,V,SLAIN","2,0,V,AILS"]},"level_005":{"a":25753,"b":"USHYB","c":7,"d":5,"e":["4,3,H,BUS","0,4,H,BUY","4,1,V,HUB","0,2,V,SUB","1,1,H,BUSH","6,1,V,BUSY","2,0,V,BUSHY"]},"level_006":{"a":25756,"b":"ASWLH","c":7,"d":6,"e":["2,3,H,LAW","0,5,H,SAW","0,3,V,WAS","6,2,VB,WASH","2,0,H,LASH","2,2,V,SLAW","4,0,V,SHAWL"]},"level_007":{"a":25757,"b":"UOHGD","c":7,"d":6,"e":["2,0,H,DOG","2,0,V,DUG","0,0,V,DUH","4,2,H,DUO","4,0,V,GOD","0,2,H,HOG","3,3,V,HUG","5,2,V,UGH","1,4,H,DOUGH"]},"level_008":{"a":19729,"b":"HTEBA","c":9,"d":9,"e":["1,4,H,ATE","5,6,V,BAT","3,8,H,BET","6,2,V,EAT","1,6,H,HAT","3,6,V,TAB","2,4,V,TEA","6,4,H,THE","5,6,H,BATH","5,0,HB,BEAT","1,1,V,BETA","7,4,V,HATE","0,2,H,HEAT","3,0,V,BATHE"]},"level_009":{"a":25760,"b":"NSOEI","c":6,"d":6,"e":["0,3,V,ION","3,3,V,ONE","4,1,V,SIN","2,3,H,SON","0,5,H,NOSE","2,0,V,EONS","1,1,H,NOISE"]},"level_010":{"a":25761,"b":"ADICR","c":9,"d":7,"e":["0,4,H,AID","4,1,H,AIR","6,0,V,ARC","6,2,H,CAR","8,2,V,RID","4,0,V,CAD","2,2,H,RAD","5,4,H,ACID","5,3,V,CARD","0,3,V,RAID","2,6,H,ARID","2,0,V,ACRID"]},"level_011":{"a":19672,"b":"INGWR","c":7,"d":6,"e":["0,4,H,GIN","4,3,H,RIG","2,2,H,WIG","0,0,H,WIN","4,2,V,GRIN","6,0,V,RING","2,2,V,WING","0,0,V,WRING"]},"level_012":{"a":25765,"b":"OHTRB","c":7,"d":6,"e":["4,1,V,ROB","4,2,H,ORB","0,1,H,BOT","6,2,V,BRO","1,0,V,BOTH","0,5,HB,BROTH","0,3,H,THROB"]},"level_013":{"a":19669,"b":"RMCIE","c":7,"d":6,"e":["6,0,V,ICE","0,2,H,RIM","4,2,H,IRE","5,2,V,REM","2,2,V,MICE","1,0,HB,RICE","2,4,H,CRIME"]},"level_014":{"a":25775,"b":"TGRAF","c":7,"d":6,"e":["0,2,H,FAR","4,2,H,FAT","2,2,V,RAG","6,0,V,AFT","1,0,HB,RAFT","4,2,V,FRAT","2,4,H,GRAFT"]},"level_015":{"a":25776,"b":"EBLOG","c":8,"d":7,"e":["0,2,H,BEG","0,2,V,BOG","0,4,H,GEL","2,4,V,LEG","5,4,V,LOB","2,0,V,LOG","4,0,V,BLOG","7,0,VB,LOBE","2,6,H,GLOB","1,0,H,GLOBE"]},"level_016":{"a":25781,"b":"ATDMI","c":8,"d":6,"e":["1,0,H,DAM","1,0,V,DIM","3,0,V,MAD","5,3,V,MAT","5,3,H,MID","7,1,V,TAD","0,2,H,AMID","0,4,HB,MAID","3,1,H,ADMIT"]}}