{"level_001":{"a":9355662,"b":"FEILN","c":7,"d":7,"e":["0,4,V,ELF","0,2,H,FEN","0,6,H,FILE","3,5,H,FINE","3,3,V,LIFE","2,0,V,LINE","5,2,V,LIEN","2,3,H,ELFIN"]},"level_002":{"a":9355699,"b":"PSGOIYS","c":8,"d":8,"e":["2,1,H,PIG","6,0,VB,SIP","0,2,H,SOY","2,0,V,SPY","2,6,H,SOP","2,4,V,OPS","0,0,V,SIS","7,4,V,YOGI","4,1,V,GOSSIP","1,4,H,GOSSIPY"],"f":1},"level_003":{"a":9355674,"b":"TSSYEM","c":6,"d":5,"e":["2,3,H,MESS","0,0,V,SETS","2,0,V,STEM","5,0,V,MESSY","0,0,H,SYSTEM"]},"level_004":{"a":9355668,"b":"THNTUUR","c":11,"d":9,"e":["7,5,V,HUT","8,1,V,NUT","6,1,H,RUN","4,0,V,URN","3,0,H,HUNT","2,6,HB,HURT","1,2,H,TURN","2,1,V,RUNT","7,7,H,THRU","6,3,H,TUTU","6,0,V,TRUTH","9,3,V,UNHURT","0,4,H,UNTRUTH"],"f":2},"level_005":{"a":9355688,"b":"AERNA","c":6,"d":6,"e":["3,1,H,EAR","0,0,V,ERA","3,3,H,RAN","0,2,H,AREA","0,5,HB,EARN","3,0,V,NEAR","5,0,V,ARENA"]},"level_006":{"a":9355705,"b":"OERTRCC","c":9,"d":8,"e":["3,0,V,ORE","5,0,V,ROT","2,2,V,TOE","6,5,V,COT","7,0,V,CORE","5,2,H,TORE","0,2,H,ROTE","4,3,V,CROC","1,4,H,RETRO","2,6,H,RECTOR","2,0,H,CORRECT"],"f":1},"level_007":{"a":9355683,"b":"SEYHCE","c":6,"d":5,"e":["3,2,V,EYE","2,4,H,SEE","2,0,V,SHE","2,0,H,SHY","4,0,V,YES","0,2,H,CHEESY"]},"level_008":{"a":9355696,"b":"ELCRYLU","c":12,"d":11,"e":["6,0,V,CELL","3,1,H,CLUE","1,4,H,CURE","6,0,H,CURL","9,0,V,LURE","8,3,H,RELY","8,3,V,RULE","4,7,V,YELL","6,5,H,CULL","4,1,V,LYRE","6,5,V,CURLY","2,4,V,ULCER","0,10,H,CRUEL","1,8,H,CRUELLY"],"f":2},"level_009":{"a":9355702,"b":"EDRIW","c":8,"d":8,"e":["6,3,V,DIRE","0,6,H,DREW","4,3,H,RIDE","0,4,V,WIDE","1,1,H,WIRE","4,0,V,WEIRD","2,0,V,WIDER","0,4,H,WIRED"]},"level_010":{"a":9355677,"b":"EGTIHY","c":8,"d":7,"e":["3,0,V,GET","0,3,V,HEY","5,0,V,THE","4,4,V,TIE","1,2,H,YET","3,0,H,GIT","2,6,H,THEY","7,0,VB,YETI","2,2,V,EIGHT","0,4,H,EIGHTY"],"f":1},"level_011":{"a":9355665,"b":"EGLMO","c":6,"d":6,"e":["5,0,V,ELM","0,3,V,GEL","2,3,V,LEG","0,5,H,LOG","2,0,H,MOLE","3,0,V,OGLE","0,3,H,GOLEM"]},"level_012":{"a":9355659,"b":"EAIERLR","c":12,"d":9,"e":["6,6,H,AIR","6,6,V,ARE","4,8,H,LIE","4,6,V,EEL","1,5,H,ERR","2,7,H,IRE","8,5,H,AIL","0,3,H,EARL","8,3,V,LIAR","2,5,V,RAIL","1,2,V,RARE","3,0,V,REAL","2,1,H,REAR","5,1,V,REEL","10,5,V,LEER","10,0,V,RILE","7,0,H,LAIR","5,3,H,EARLIER"],"f":2},"level_013":{"a":9355693,"b":"RPSNU","c":7,"d":5,"e":["0,4,H,SUN","4,0,V,UPS","4,4,H,PUN","4,2,H,SUP","0,2,V,PUS","6,1,V,SPUN","2,0,H,SPUR","2,0,V,SPURN"]},"level_014":{"a":9355671,"b":"EWDGAG","c":10,"d":9,"e":["6,5,V,AGE","4,7,H,AWE","2,6,V,DEW","8,0,V,EGG","4,6,V,GAG","5,5,H,WAD","2,8,H,WAG","0,6,H,WED","1,4,H,AGED","1,3,V,WADE","6,2,H,WAGE","7,2,V,AWED","4,0,V,WAGED","4,0,H,WAGGED"],"f":1},"level_015":{"a":9355708,"b":"DFFHEU","c":7,"d":6,"e":["5,0,V,DUE","4,5,H,DUH","4,2,H,FED","0,0,V,HUE","4,2,V,FEUD","2,2,VB,HUFF","0,0,H,HUFFED"]},"level_016":{"a":9355680,"b":"NVOELC","c":14,"d":10,"e":["6,7,V,CON","1,4,H,CONE","6,7,H,COVE","4,9,H,LONE","8,5,V,LOVE","3,3,V,ONCE","9,3,H,OVEN","6,5,H,VOLE","4,6,V,NOEL","9,1,V,CLONE","11,0,V,NOVEL","9,1,H,CLOVE","0,6,H,COVEN","1,4,V,CLOVEN"],"f":2}}