{"level_001":{"b":"ENDESA","c":13,"d":10,"e":["2,6,H,END","4,5,H,ENS","4,5,V,EDS","6,4,V,ESE","0,7,H,ESA","0,5,H,EAN","10,0,V,NES","2,5,V,NEA","8,2,V,AED","8,2,H,ANS","6,4,H,ENDE","9,0,H,ENED","0,5,V,EDESA","1,0,V,ENDESA"]},"level_002":{"b":"STARTER","c":13,"d":13,"e":["5,4,H,STA","5,4,V,STE","7,3,V,SAR","7,3,H,SAE","0,8,H,STAR","9,1,H,STAT","9,1,V,SAER","12,0,V,STTE","1,5,H,START","3,4,V,SARTRE","0,6,V,RESTART"]},"level_003":{"b":"PIELAGO","c":16,"d":15,"e":["11,3,V,PIE","11,3,H,PIA","9,4,V,PIO","9,4,H,POI","7,6,V,EOG","5,8,V,PIEL","3,11,H,PILA","12,1,H,PELI","3,11,V,PELA","6,6,H,PELO","5,8,H,PEGA","0,9,H,ILEO","0,12,H,PALE","13,0,V,PEGAO","1,8,V,PLEGA","3,5,V,PALIO","15,0,V,PIELAGO"]},"level_004":{"b":"LAWYERS","c":10,"d":9,"e":["8,2,V,LEAS","6,0,V,LESA","6,3,H,AYER","0,2,H,AYES","6,5,V,AYRE","3,0,H,YAEL","5,5,H,LAWS","3,0,V,YASER","0,1,V,LAWYERS"]},"level_005":{"b":"ESTILOS","c":15,"d":15,"e":["8,9,V,EST","6,10,V,ESO","6,10,H,ETS","4,11,V,ETL","4,11,H,ELS","2,13,H,TOL","0,11,H,ISE","2,11,V,ESTO","11,5,H,ESOL","1,8,V,ESOS","1,8,H,ELIO","8,9,H,ETILO","12,5,V,STILO","14,0,V,SISTOLE"]},"level_006":{"b":"ALABADO","c":11,"d":13,"e":["4,3,H,ALAD","0,8,H,ALBA","7,1,V,ALDO","7,1,H,ABAD","3,6,H,ABDO","9,0,V,LABO","5,3,V,LOAD","3,6,V,ALABA","0,6,V,ALABADO"]},"level_007":{"b":"GRUMOS","c":13,"d":15,"e":["5,8,V,GRO","5,8,H,GUS","7,0,V,GOM","7,6,H,RUM","9,4,V,ROM","6,0,H,UGR","3,10,H,URO","7,6,V,RUSO","9,4,H,ROMS","0,12,H,MURO","11,2,V,SUMO","7,2,H,MUROS","3,8,V,GRUMO","0,9,V,GRUMOS"]},"level_008":{"b":"CUAUTLA","c":16,"d":13,"e":["5,7,V,CUA","5,7,H,CUT","7,5,V,CAT","9,3,V,UTL","0,6,H,CUAL","2,9,H,CATA","7,5,H,CALA","9,3,H,UCAT","11,0,V,UCLA","11,1,H,CULTA","15,1,V,ACTUA","3,4,V,CULATA","0,6,V,CUAUTLA"]},"level_009":{"b":"ROSETE","c":15,"d":13,"e":["8,5,V,ROS","7,7,V,ROE","7,7,H,RSE","8,5,H,ROSE","11,4,H,ROTE","6,9,H,REOS","6,9,V,RESO","4,11,H,REST","4,9,V,OTRS","11,2,V,SORE","0,9,H,RESTO","2,5,V,RETOS","1,7,H,STEER","13,0,V,ROSETE"]},"level_010":{"b":"PIÑATAS","c":14,"d":15,"e":["4,12,H,PIA","4,12,V,PIT","2,13,H,PAI","1,11,H,ÑAS","2,11,V,AIP","1,6,V,PIÑA","6,9,H,PITA","1,6,H,PISA","3,8,V,PAIS","0,9,H,PATA","4,4,V,PAAS","4,4,H,PASA","6,1,V,PTAS","6,1,H,PIÑAS","9,0,V,PAITA","9,4,H,ATIAS","6,9,V,PIÑATA","8,5,V,PIÑATAS"]},"level_011":{"b":"CAJONES","c":14,"d":12,"e":["5,6,H,CAN","7,4,H,CAE","5,6,V,CAS","7,4,V,CON","3,8,H,COS","3,8,V,CAOS","0,10,H,CANO","9,1,V,CANE","9,1,H,CAJON","12,0,V,CONSEJA"]},"level_012":{"b":"MESSINA","c":16,"d":14,"e":["10,3,V,MES","8,5,V,MEN","8,5,H,MIS","6,6,V,MIA","6,6,H,MAE","3,8,V,MSE","12,5,H,MESA","2,10,H,MEIN","3,8,H,MENA","2,10,V,MIES","15,2,V,ESIA","0,13,H,MESSI","10,3,H,MESIAS","13,0,V,MANISES"]},"level_013":{"b":"VERSEN","c":12,"d":15,"e":["9,6,V,VER","9,6,H,VES","5,10,V,VEN","7,7,H,EVE","9,4,H,ENR","7,2,H,VERS","5,10,H,VERE","7,7,V,EVER","11,3,V,ERES","3,11,V,ENES","2,11,H,REVE","0,14,H,REES","9,0,V,VERSE","7,0,V,NEVERS"]},"level_014":{"b":"FUNDES","c":8,"d":10,"e":["1,9,H,FUND","4,6,H,UNED","0,1,H,UNES","5,3,V,USEN","4,6,V,USED","3,3,H,NEUS","3,1,V,SUNDE","0,0,V,FUNDES"]},"level_015":{"b":"DORMIA","c":16,"d":12,"e":["5,8,V,DOR","5,8,H,DOI","7,9,H,DRA","3,9,H,DIO","7,7,V,RID","8,6,H,IDR","9,6,V,DORA","0,7,H,DRAM","8,2,H,DIMA","11,0,V,ORAD","8,2,V,DORMI","11,3,H,DARIO","3,7,V,MADRI","2,2,V,DORMIA"]},"level_016":{"b":"ARENDT","c":13,"d":15,"e":["7,3,H,ARE","7,3,V,ARN","5,4,V,ART","5,4,H,AER","3,6,V,AED","1,8,V,AEN","1,8,H,ARDE","9,5,H,ARTE","0,10,H,ANDE","3,6,H,ANTE","2,12,H,RAND","9,2,V,REDA","3,10,V,ERAT","5,10,V,ANDRE","5,10,H,ANDER","11,0,V,ARENDT"]},"level_017":{"b":"LACADO","c":12,"d":12,"e":["7,0,V,LAC","5,2,V,LCA","3,4,H,LOA","5,2,H,LOC","7,1,H,ALC","9,4,H,ALA","3,3,V,ALD","1,3,V,ALO","2,5,V,ADL","0,3,H,LACA","0,5,H,LOAD","1,7,H,ALCO","3,7,V,CALDO","9,1,V,CADAL","11,3,V,LACADO"]},"level_018":{"b":"DESTAPE","c":10,"d":11,"e":["2,8,H,DES","4,6,H,DEA","2,8,V,DEP","0,9,H,DTE","4,6,V,DAS","6,3,V,DESA","5,4,H,DESEA","9,0,V,DESTAPE"]},"level_019":{"b":"YBARRA","c":14,"d":12,"e":["10,7,V,YBR","8,9,H,YAR","8,7,V,BAY","6,8,V,BAR","6,8,H,BAA","10,3,H,RRA","10,7,H,YBRA","4,10,H,YARA","4,7,V,BRAY","1,9,H,ABRA","1,8,V,RAYA","0,11,H,RARA","12,3,V,AYBAR","10,0,V,YBARRA"]},"level_020":{"b":"GRELIS","c":10,"d":12,"e":["4,1,H,GRIS","6,0,V,GIRE","4,1,V,GIRL","0,7,H,RESI","7,3,V,RIGE","6,3,H,ERIS","1,4,H,GIRLS","1,4,V,GISEL","3,6,V,SIGLER"]},"level_021":{"b":"ADONAIS","c":14,"d":10,"e":["6,6,V,ADAN","6,6,H,ANDO","0,4,H,ANDA","8,4,V,ANDI","8,4,H,ANIO","10,2,V,ANIS","10,2,H,ANSI","2,8,H,ANDIA","2,3,V,ODINSA","0,0,V,ANSIADO"]},"level_022":{"b":"SIRION","c":15,"d":14,"e":["10,5,V,SIR","8,6,H,SII","8,6,V,SIO","6,7,V,SIN","6,7,H,SRI","10,5,H,SRO","4,9,V,SOR","4,9,H,SON","12,3,H,SNI","2,11,H,ISR","0,10,H,ORS","12,3,V,SNO","2,10,V,SIRI","0,8,V,SION","0,8,H,SINO","3,4,V,SIRIO","14,0,V,SIRION"]},"level_023":{"b":"PISTONS","c":12,"d":15,"e":["4,4,H,PISO","0,8,H,PINT","2,6,H,PINO","7,2,V,PION","7,2,H,PISON","5,3,V,PISOS","11,0,V,PINTO","3,5,V,PISTON","0,8,V,PISTONS"]},"level_024":{"b":"LISTAS","c":14,"d":13,"e":["9,1,V,LIST","12,3,V,LISA","10,5,H,LISS","4,2,H,LIAS","10,5,V,LAST","7,1,H,ISLA","8,7,H,ISSA","8,7,V,ITSA","9,3,H,SIAL","6,9,H,SISA","6,8,V,LSSI","3,8,V,LISTA","7,0,V,LISAS","2,10,H,ISLAS","0,12,H,ISTAS","5,1,V,LISTAS"]},"level_025":{"b":"VUELTA","c":11,"d":14,"e":["2,6,H,VELA","5,3,V,VETA","7,0,H,VALE","2,6,V,VATE","1,9,H,LEVA","9,0,V,LAVE","0,12,H,EVAL","3,9,V,VUELA","5,3,H,VALUE","7,0,V,VUELTA"]},"level_026":{"b":"PROVAR","c":9,"d":11,"e":["4,1,V,PRO","2,2,V,PRA","2,2,H,POR","0,4,H,POA","0,4,V,PAR","4,1,H,PAO","0,6,H,ROP","0,8,V,ROA","6,2,H,RAP","0,8,H,RRO","2,6,V,PROV","6,0,V,PORA","8,2,V,PROVAR"]},"level_027":{"b":"CERRARE","c":14,"d":15,"e":["9,3,V,CER","7,4,V,CEA","7,4,H,CEE","5,5,H,CRE","9,3,H,CRA","11,1,H,CAE","5,5,V,CAR","3,7,H,ECR","3,7,V,ECA","0,9,H,CERA","2,9,V,RARE","11,1,V,CEAR","0,11,H,CERRA","4,10,V,CAERE","3,13,H,CREARE","13,0,V,RECREAR"]},"level_028":{"b":"NARCOS","c":11,"d":14,"e":["5,4,H,NAC","3,6,H,NAS","6,2,V,NRA","6,2,H,NRO","8,1,V,NOA","8,1,H,NOR","5,4,V,NOS","8,3,H,ANS","10,0,V,NROS","0,5,H,NORA","6,7,H,ARNO","6,7,V,ARCO","4,10,H,ARON","4,10,V,AROS","1,11,H,CNAR","9,3,V,NARCO","3,4,V,CANOS","1,1,V,NARCOS"]},"level_029":{"b":"JUNGLAS","c":9,"d":9,"e":["0,6,V,JUG","2,6,H,JAN","2,6,V,JAL","0,7,H,UNA","3,4,V,ULA","2,4,H,JUNG","4,1,V,JUAN","4,1,H,JANUS","7,0,V,JUNGLAS"]},"level_030":{"b":"VIGILIA","c":12,"d":15,"e":["3,9,H,VIGA","6,6,V,VILA","8,4,H,VIAL","4,8,V,GILI","3,11,H,GILA","3,11,V,GALI","0,12,H,LIGA","5,7,H,VIGIA","9,3,V,LIGIA","11,0,V,VIGILIA"]},"level_031":{"b":"PANTYS","c":10,"d":12,"e":["4,7,H,PATY","1,8,V,PAYS","6,5,H,PNAS","1,8,H,PTAS","0,11,H,PSAT","4,5,V,TAPS","7,3,V,PANTY","9,0,V,PANTYS"]}}