{"level_001":{"b":"OLNZASA","c":15,"d":10,"e":["3,5,V,ZONAS","4,2,V,ZONA","0,5,H,LANZAS","2,8,H,LAZO","5,7,H,SAZON","7,5,V,ALZO","10,2,H,LANZO","7,5,H,ALZAS","5,7,V,SOL","11,1,V,LAZOS","13,0,V,LOZANAS"]},"level_002":{"b":"ALVCODA","c":13,"d":12,"e":["8,2,V,CAVADO","9,1,H,LADA","6,5,H,AVALO","10,0,V,LAVADO","6,4,V,CAVA","7,3,H,VACA","2,7,H,CLAVADO","12,0,V,LADO","4,6,V,LAVA","2,7,V,CALDO","0,9,H,VOLCADA"]},"level_003":{"b":"LOOADCM","c":11,"d":8,"e":["7,6,HB,MODO","0,5,H,DOMO","1,2,V,COLO","5,4,V,COMO","5,4,H,COLADO","3,4,V,LOMO","6,1,V,MALO","1,7,H,ACODO","3,1,H,COLMADO","4,0,V,MODA"]},"level_004":{"b":"OLSREIF","c":8,"d":8,"e":["5,0,V,LEO","3,4,H,FIEL","3,0,H,ROLES","6,2,V,SILO","0,5,H,OLER","0,2,V,FILO","3,4,V,FREI","0,2,H,FRIELOS"]},"level_005":{"b":"ONOREAG","c":10,"d":10,"e":["4,2,H,NEGAR","4,8,H,GEN","6,6,H,GANE","6,0,V,NEGRA","2,6,H,ORA","6,6,V,GANO","2,4,V,ARO","4,5,V,RANGO","0,4,H,ERAN","0,4,V,EGO","8,1,V,OREGANO"]},"level_006":{"b":"TRAARET","c":11,"d":11,"e":["0,7,H,TARTA","1,3,V,TAREA","1,3,H,TRAER","3,0,V,RATA","1,1,H,TRATAR","5,1,V,ATRAE","6,5,V,TATA","6,7,H,TRATE","4,5,H,RETRATA","3,7,V,TRAE","8,3,V,TRATARE"]},"level_007":{"b":"CROOSOT","c":21,"d":14,"e":["4,2,H,ROTO","9,4,V,SORO","5,4,H,TOROS","0,3,H,CORTO","6,1,V,OTROS","2,2,V,OROS","1,5,H,OSO","2,8,H,CORSO","6,7,V,COSTO","5,11,H,CORTOS","4,0,V,TORO","10,8,V,TORSO","9,9,H,TOCO","12,8,V,COROS","3,5,V,OTRO","12,10,H,ROTOS","16,6,V,COTOS","16,8,H,TOSCO","20,7,V,COROTOS"]},"level_008":{"b":"MCAEENA","c":10,"d":7,"e":["8,0,V,CENA","0,2,H,CAMA","4,3,H,AMENA","3,0,V,ACA","1,0,V,EMANA","4,3,V,ACNE","3,0,H,AMANECE","2,6,H,AMENACE"]},"level_009":{"b":"PIOSMEN","c":16,"d":16,"e":["4,11,V,MESON","1,9,V,PIE","3,13,H,ESPINO","13,11,V,PEON","11,11,V,PONE","1,9,H,PIO","0,11,H,PESIMO","8,12,H,IMPONE","12,3,V,MIS","3,6,H,PIN","5,4,V,PONES","3,6,V,PISO","5,7,H,ESPIN","9,5,V,PINOS","8,11,V,MIOS","9,5,H,PENSO","8,14,H,SONE","12,3,H,MINO","15,0,V,IMPONES"]},"level_010":{"b":"AEAVSRN","c":19,"d":13,"e":["15,8,H,VANA","18,2,V,ARENA","16,2,H,VEA","16,0,V,NAVES","14,6,H,VERSA","12,4,H,ARNES","14,1,V,VEAN","7,4,H,VEN","12,2,V,ARAS","9,2,V,VENA","17,6,V,SANEAR","7,4,V,VARA","3,6,H,SANAR","9,5,H,ARES","5,4,V,RANAS","0,8,H,ARENAS","11,2,H,NAVE","1,6,V,VARAS","15,6,V,ENVASAR"]},"level_011":{"b":"HAARROC","c":15,"d":10,"e":["3,1,VB,ARCO","7,0,V,HARA","0,6,H,AHORCAR","5,1,V,AHORRA","10,3,V,CHAO","5,1,H,ACARO","8,3,V,RARA","10,3,H,CARRO","5,3,H,ORAR","7,5,H,CROAR","3,6,V,ROCA","12,1,V,RARO","11,1,H,ARCA"]},"level_012":{"b":"AAECRHC","c":13,"d":13,"e":["9,0,V,ARCE","6,0,V,CACHE","8,2,H,ECHAR","1,1,H,ACERCA","1,1,V,ACECHA","6,0,H,CARA","1,3,H,ECHA","3,3,V,HARE","5,6,H,CHECAR","11,1,V,CAERA","8,6,V,CACHEAR","0,5,H,CHARCA","5,5,V,ACECHAR"]},"level_013":{"b":"NIARSPE","c":17,"d":16,"e":["5,4,H,PRISA","5,4,V,PAREN","0,5,H,PIENSA","7,6,H,PRENSA","1,4,V,PISAR","0,8,H,ERAS","3,8,V,SAN","1,10,H,RIN","8,4,V,SERAN","1,15,H,AIRE","3,12,H,PAN","3,12,V,PIAR","1,10,V,RESINA","12,10,V,PIA","7,12,H,PIERNAS","5,10,H,REINA","5,10,V,RINES","9,9,V,PASE","12,10,H,PINAR","11,0,V,PINARES"]},"level_014":{"b":"ATAORAP","c":17,"d":17,"e":["13,4,H,TOPA","11,0,H,APARTA","11,0,V,ATRAPA","9,2,H,PORTA","6,3,H,TARA","9,2,V,PARA","7,3,V,APORTA","4,5,H,PATO","16,2,V,ATAR","5,4,V,TAPA","3,6,V,RAPTO","2,7,H,PATA","1,9,H,APTO","13,0,V,APARTO","0,12,H,TRAPO","4,12,V,OPTAR","1,9,V,APARATO"]},"level_015":{"b":"INIEGER","c":10,"d":7,"e":["0,5,H,GIRE","3,2,V,RIGE","5,1,V,RIEN","2,3,H,RIGEN","5,1,H,REINE","0,2,V,RING","8,0,V,INGIERE"]},"level_016":{"b":"SIRVPAE","c":15,"d":15,"e":["10,9,V,SPA","7,11,V,RIE","5,12,H,ASI","2,10,H,SIRVE","13,6,V,VEIA","7,11,H,RISA","10,9,H,SEPA","10,5,V,RIA","10,7,H,AIRES","7,1,H,PRESA","9,5,H,IRE","11,1,V,AVISE","2,10,V,SERVI","5,10,V,VIAS","8,0,V,PRIVA","2,4,H,VISPERA","6,3,V,VEIAS","0,7,H,PREVIAS"]}}