{"level_001":{"b":"CUEPTOA","c":14,"d":10,"e":["8,0,V,AUTO","4,0,H,OCUPA","4,3,H,PACTO","13,2,V,PUE","0,6,H,OCUPE","10,4,H,TOPE","7,5,H,COPA","0,6,V,OPTE","7,3,V,TOCA","10,1,V,CUOTA","4,0,V,OCUPATE"]},"level_002":{"b":"ESNCIII","c":9,"d":9,"e":["4,1,H,CISNE","7,0,V,INICIE","0,6,H,SIN","2,4,V,CINES","4,1,V,CIEN","2,4,H,CINE","0,0,V,INICIES"]},"level_003":{"b":"EOARTRM","c":17,"d":13,"e":["1,6,V,ROTA","4,8,V,MOR","4,10,H,RAMO","6,3,V,MATE","6,9,V,AMOR","0,7,H,TOMA","3,6,H,TOME","1,12,H,MOTEAR","0,9,H,MAREO","3,4,V,RETA","3,4,H,REMATO","8,0,V,RETRO","2,9,V,RARO","11,2,V,AMO","8,2,H,TOMARE","14,3,V,REMO","11,6,H,REMOTA","10,4,H,MOARE","16,1,V,RETOMAR"]},"level_004":{"b":"CBRAERO","c":14,"d":14,"e":["4,5,H,BARCO","6,1,H,OBRE","4,5,V,BORRA","0,6,H,ACERO","1,6,V,CERRO","0,9,H,BROCA","8,0,V,BRACEO","3,9,V,CORRE","3,11,H,ROBAR","7,8,V,COBRAR","6,9,H,CORRA","10,4,H,ERRO","9,6,V,COBRA","9,6,H,CROAR","11,2,V,BARRO","6,0,V,COBRARE"]},"level_005":{"b":"IUSSLO","c":10,"d":7,"e":["3,4,V,SOL","1,4,H,LOS","7,1,V,LIOS","2,2,H,USOS","5,0,V,SOS","5,4,H,LISOS","2,2,V,USO","1,6,H,SILOS","5,4,V,LIS","0,0,H,ILUSOS"]},"level_006":{"b":"GNJSEAU","c":10,"d":10,"e":["0,4,H,UNASE","2,2,H,JUGASE","2,2,V,JEAN","0,7,H,SENA","7,0,V,SUENA","0,4,V,UNES","3,6,V,GAJE","3,8,H,JUGASEN"]},"level_007":{"b":"IATRAD","c":10,"d":9,"e":["0,4,H,TIRADA","4,7,H,TARDIA","5,3,V,DARIA","3,2,V,ATAR","6,0,V,DARA","7,3,V,TRAIDA","5,3,H,DATA","2,0,H,TRIADA"]},"level_008":{"b":"ORPEDTO","c":14,"d":12,"e":["1,1,HB,TOPO","2,5,V,OPTE","4,10,H,PODER","3,3,V,POR","0,8,H,OPERO","6,5,V,TORPEDO","2,5,H,ORO","7,0,V,TODO","3,3,H,PORTO","6,1,H,RODO","9,1,V,OTRO","4,7,V,TORPE","8,4,H,TOPE","8,7,H,OPTO","8,4,V,TORO","11,6,H,PRO","11,6,V,PODRE","13,5,V,POTRO"]},"level_009":{"b":"BTEEIML","c":10,"d":7,"e":["6,6,H,TEME","2,2,V,LEI","4,2,H,METE","4,2,V,MIEL","7,2,V,ELITE","0,4,H,EMITE","9,0,V,TEMIBLE"]},"level_010":{"b":"ADRNIU","c":13,"d":9,"e":["7,0,V,UNI","3,3,H,URNA","3,2,V,RUINA","7,4,H,DIURNA","8,3,V,RINDA","5,1,H,DAN","5,1,V,DUNAR","10,0,V,DINAR","7,0,H,UNIDA","0,5,H,RUIN","0,3,V,DURIAN"]},"level_011":{"b":"REASEDL","c":17,"d":16,"e":["11,7,H,REALES","11,4,H,DESEAR","14,0,V,ERASE","15,6,V,SERLE","14,10,H,RES","13,4,V,SERA","11,13,H,LASER","14,10,V,REDES","12,9,V,DESEA","9,11,H,ERES","9,7,V,DARLE","7,6,V,LEASE","5,6,H,DALE","5,6,V,DARLES","3,10,H,ESE","7,9,H,SERE","3,10,V,ERAS","0,11,V,LADRE","0,13,H,DARSELE"]},"level_012":{"b":"ILMFAR","c":12,"d":9,"e":["2,7,H,LIRA","6,0,V,FIRMA","0,5,H,RIFA","2,5,V,FILA","6,0,H,FILMAR","5,4,V,MIRA","0,4,V,IRA","5,4,H,MARFIL"]},"level_013":{"b":"ARNFLOA","c":14,"d":10,"e":["2,2,V,LANAR","0,4,H,FAN","5,0,V,FARAON","2,2,H,LOAR","5,0,H,FAROLA","10,0,V,AFANO","10,2,H,AFAN","13,0,V,RON","0,3,V,AFLORAN"]},"level_014":{"b":"DSEFOU","c":12,"d":8,"e":["4,1,V,DES","2,3,H,DOS","6,0,V,FEO","4,2,H,ESO","0,5,H,FEOS","2,3,V,DUO","9,0,V,DUOS","0,5,V,FUE","6,0,H,FEUDOS"]},"level_015":{"b":"FEADRER","c":10,"d":7,"e":["8,0,V,FERREA","6,2,V,DAR","0,4,V,FEA","6,2,H,DARE","0,6,H,ARE","0,4,H,FEDERAR"]},"level_016":{"b":"DECINAE","c":14,"d":10,"e":["0,6,H,ENCIA","1,1,V,ENDE","0,1,H,DECIA","0,4,H,CEDE","4,3,H,EDEN","4,0,V,NACE","0,4,V,CAEN","2,4,V,DECIAN","7,2,V,ANDE","7,5,H,EDENICA"]}}