{"level_001":{"b":"BAERULO","c":12,"d":12,"e":["4,1,H,ARBOL","8,7,H,BULA","5,3,V,ORE","4,0,V,BAUL","8,4,H,ABRE","8,1,V,LOBA","3,5,H,UREA","8,7,V,BURLA","4,5,V,REO","0,3,H,ABUELO","10,2,V,BOREAL","0,7,H,RUBEOLA"]},"level_002":{"b":"NGADLOI","c":18,"d":13,"e":["3,7,H,DOGAL","5,7,V,GOL","0,5,H,NIDO","1,3,V,ODIAN","8,8,V,DOLIA","1,3,H,OIDA","5,9,H,LAGO","7,11,H,LIGADO","10,8,V,NOGAL","3,5,V,ONDA","8,8,H,DAN","14,3,H,AGIL","9,6,H,LINDO","11,3,V,DIGNO","9,6,V,LIA","10,4,H,DIGAN","4,1,V,IDA","14,0,V,OIGAN","16,2,V,LIGANDO"]},"level_003":{"b":"ERVNALA","c":11,"d":11,"e":["6,6,H,VELA","4,8,V,VER","1,9,H,NAVE","2,6,V,VELAR","6,6,V,VALEN","2,6,H,VAN","3,4,V,ARA","9,1,V,VELARA","0,4,H,VERAN","2,0,V,LANAR","0,1,H,VEAN","4,8,H,VELARAN"]},"level_004":{"b":"CCASAIL","c":10,"d":7,"e":["0,3,H,ALIAS","6,1,V,CLIC","1,1,V,CAL","9,0,V,LAICA","0,3,V,ALAS","6,4,H,CASA","1,1,H,CLASICA"]},"level_005":{"b":"LILRVA","c":10,"d":7,"e":["2,3,H,VAL","8,2,VB,VIAL","4,0,H,VILLAR","2,1,V,RIVAL","0,5,H,IRLA","0,4,V,VIL","6,0,V,LIRA","4,0,V,VILLA"]},"level_006":{"b":"TLPEAI","c":8,"d":8,"e":["4,5,V,PIE","1,7,H,TAPE","4,2,H,PIEL","4,5,H,PILA","5,1,V,PIA","2,4,V,LEIA","0,4,H,TILA","7,0,V,PILETA"]},"level_007":{"b":"SAEOSIG","c":10,"d":10,"e":["4,3,H,OSEAS","3,7,H,GASES","8,3,V,SIGA","3,7,V,GAS","5,0,V,SEAS","0,9,H,SEIS","0,6,H,EGO","5,5,V,SOS","0,6,V,ESAS","3,5,H,SOSIEGA"]},"level_008":{"b":"OAREDMI","c":14,"d":14,"e":["10,7,H,AME","11,7,V,MIDO","9,9,H,MADRE","9,0,V,REIA","8,1,H,MEDRO","6,11,H,DIERA","9,9,V,MIRO","6,9,V,ARDE","3,9,H,MODA","3,9,V,MEDIO","1,7,V,REMA","0,10,H,DAME","1,7,H,RAMO","0,2,H,MEDIR","2,2,V,DEMORA","0,2,V,MERA","12,1,V,ODIARME"]},"level_009":{"b":"TAMABON","c":10,"d":9,"e":["0,4,H,AMAN","5,0,V,ABONA","3,2,V,MANTO","1,2,H,TAMBO","5,4,H,ANOTA","7,3,V,TOMAN","1,2,V,TOMABAN"]},"level_010":{"b":"ALRAZOF","c":11,"d":8,"e":["0,2,V,ROZA","2,4,H,FARO","0,2,H,RAZA","3,2,V,AZAR","5,6,H,ZAR","7,2,H,ALZO","9,0,V,FAZ","7,2,V,AZOFRA","5,1,V,ALFORZA"]},"level_011":{"b":"UEDLNZO","c":8,"d":8,"e":["0,3,V,DUELO","6,3,V,UNO","7,0,V,NUEZ","2,1,V,ZEN","5,3,H,LUZ","0,3,H,DEN","0,5,H,ENDULZO"]},"level_012":{"b":"OSTJORI","c":13,"d":13,"e":["0,2,H,OROS","5,0,V,OSO","2,0,V,TIOS","5,2,H,OIR","2,0,H,TORO","7,1,V,TRIOS","3,5,H,ROJOS","2,7,V,TIROS","3,4,V,TRIO","2,7,H,TORIO","2,10,H,ORO","4,10,V,OJO","3,12,H,ROJO","0,2,V,OJITOS","6,9,V,RISO","6,9,H,ROJITOS"]},"level_013":{"b":"APEBELA","c":9,"d":7,"e":["4,0,V,BALA","4,1,H,APELA","6,3,H,ALA","8,0,V,PALA","0,3,H,PELEA","0,3,V,PELE","6,3,V,ALBA","2,6,H,PELEABA"]},"level_014":{"b":"NIAODMA","c":12,"d":9,"e":["8,5,H,ANDO","3,2,H,NOMADA","3,0,V,MANDO","10,1,V,MINADO","6,0,V,IMAN","0,4,H,NADO","1,1,V,MONA","3,0,H,MANIA","8,2,V,ANDAMIO"]},"level_015":{"b":"MREICOD","c":9,"d":6,"e":["5,0,V,MIRE","4,3,H,RECIO","4,3,V,RIE","0,0,V,MEDICO","2,0,V,DECIR","0,2,H,DOCE","2,0,H,DERMICO"]},"level_016":{"b":"IRCATNI","c":15,"d":10,"e":["13,4,V,TIA","11,5,V,CINTA","11,5,H,CRIA","7,3,V,INCITA","5,4,H,TINA","3,1,H,RIN","7,7,H,TIRAN","0,2,H,NACI","3,1,V,RICA","5,0,V,INCITAR"]}}